llm_content_filter/__init__.py
llm_content_filter/filter.py
llm_content_filter-0.2.7.dist-info/LICENSE
llm_content_filter-0.2.7.dist-info/METADATA
llm_content_filter-0.2.7.dist-info/WHEEL
llm_content_filter-0.2.7.dist-info/entry_points.txt
llm_content_filter-0.2.7.dist-info/top_level.txt
llm_content_filter-0.2.7.dist-info/RECORD
