Metadata-Version: 2.1
Name: llm-content-filter
Version: 0.2.7
Summary: A simple and customizable content filter for LLMs
Home-page: https://github.com/jclanas2019/llm_content_filter
Author: Juan Carlos Lanas Ocampo
Author-email: juancarlos.lanas.ocampo@gmail.com
Project-URL: Bug Reports, https://github.com/jclanas2019/llm_content_filter/issues
Project-URL: Source, https://github.com/jclanas2019/llm_content_filter/
Keywords: LLM content filter NLP text moderation
Classifier: Development Status :: 4 - Beta
Classifier: Intended Audience :: Developers
Classifier: Topic :: Software Development :: Libraries :: Python Modules
Classifier: Programming Language :: Python :: 3
Classifier: Programming Language :: Python :: 3.6
Classifier: Programming Language :: Python :: 3.7
Classifier: Programming Language :: Python :: 3.8
Classifier: Programming Language :: Python :: 3.9
Classifier: Programming Language :: Python :: 3.10
Classifier: License :: OSI Approved :: MIT License
Classifier: Operating System :: OS Independent
Classifier: Natural Language :: English
Requires-Python: >=3.6
License-File: LICENSE
Requires-Dist: jsonschema >=3.2.0
Provides-Extra: dev
Requires-Dist: check-manifest ; extra == 'dev'
Provides-Extra: test
Requires-Dist: coverage ; extra == 'test'
